bin/__init__.py
namecom/__init__.py
namecom/cli.py
namecom/compat.py
namecom/helpers.py
namecom-0.3.0.data/scripts/namecli
namecom-0.3.0.dist-info/LICENSE.txt
namecom-0.3.0.dist-info/METADATA
namecom-0.3.0.dist-info/WHEEL
namecom-0.3.0.dist-info/top_level.txt
namecom-0.3.0.dist-info/RECORD
