Metadata-Version: 2.1
Name: namecom
Version: 0.3.0
Summary: Python SDK for name.com
Home-page: https://github.com/fzlee/namecom
Author: fzlee
Author-email: hi@ifconfiger.com
License: UNKNOWN
Project-URL: Bug Reports, https://github.com/fzlee/namecom/issues
Project-URL: Source, https://github.com/fzlee/namecom/
Keywords: name.com v4 sdk
Platform: UNKNOWN
Classifier: Development Status :: 5 - Production/Stable
Classifier: Intended Audience :: Developers
Classifier: Topic :: Software Development :: Build Tools
Classifier: License :: OSI Approved :: MIT License
Classifier: Programming Language :: Python :: 2.7
Classifier: Programming Language :: Python :: 3.3
Classifier: Programming Language :: Python :: 3.4
Classifier: Programming Language :: Python :: 3.5
Classifier: Programming Language :: Python :: 3.6
Classifier: Programming Language :: Python :: 3.7
Requires-Dist: click
Requires-Dist: requests
Provides-Extra: dev
Requires-Dist: check-manifest ; extra == 'dev'
Provides-Extra: test
Requires-Dist: coverage ; extra == 'test'
